atomate/__init__.py
atomate/common/__init__.py
atomate/common/powerups.py
atomate/common/firetasks/__init__.py
atomate/common/firetasks/glue_tasks.py
atomate/common/firetasks/parse_outputs.py
atomate/common/firetasks/run_calc.py
atomate/feff/__init__.py
atomate/feff/database.py
atomate/feff/firetasks/__init__.py
atomate/feff/firetasks/glue_tasks.py
atomate/feff/firetasks/parse_outputs.py
atomate/feff/firetasks/run_calc.py
atomate/feff/firetasks/write_inputs.py
atomate/feff/fireworks/__init__.py
atomate/feff/fireworks/core.py
atomate/feff/workflows/__init__.py
atomate/feff/workflows/core.py
atomate/feff/workflows/presets.py
atomate/lammps/__init__.py
atomate/lammps/database.py
atomate/lammps/drones.py
atomate/lammps/utils.py
atomate/lammps/firetasks/__init__.py
atomate/lammps/firetasks/glue_tasks.py
atomate/lammps/firetasks/parse_outputs.py
atomate/lammps/firetasks/run_calc.py
atomate/lammps/firetasks/write_inputs.py
atomate/lammps/fireworks/__init__.py
atomate/lammps/fireworks/core.py
atomate/lammps/workflows/__init__.py
atomate/lammps/workflows/core.py
atomate/qchem/__init__.py
atomate/qchem/database.py
atomate/qchem/drones.py
atomate/qchem/powerups.py
atomate/qchem/firetasks/__init__.py
atomate/qchem/firetasks/critic2.py
atomate/qchem/firetasks/fragmenter.py
atomate/qchem/firetasks/geo_transformations.py
atomate/qchem/firetasks/parse_outputs.py
atomate/qchem/firetasks/run_calc.py
atomate/qchem/firetasks/write_inputs.py
atomate/qchem/fireworks/__init__.py
atomate/qchem/fireworks/core.py
atomate/qchem/workflows/__init__.py
atomate/qchem/workflows/base/FF_and_critic.py
atomate/qchem/workflows/base/__init__.py
atomate/qchem/workflows/base/double_FF_opt.py
atomate/qchem/workflows/base/fragmentation.py
atomate/qchem/workflows/base/reaction_path.py
atomate/qchem/workflows/base/torsion_potential.py
atomate/utils/__init__.py
atomate/utils/database.py
atomate/utils/fileio.py
atomate/utils/testing.py
atomate/utils/utils.py
atomate/vasp/__init__.py
atomate/vasp/config.py
atomate-1.1.0.dist-info/LICENSE
atomate-1.1.0.dist-info/METADATA
atomate-1.1.0.dist-info/WHEEL
atomate-1.1.0.dist-info/top_level.txt
atomate-1.1.0.dist-info/RECORD
